<?xml version="1.0" encoding="utf-8"?>
<scene>

    <camera>
        <transform type="lookat">
            <eye value="-764.0 309.0 -380.0"/>
            <center value="0.0 0.0 0.0"/>
            <up value="0.0 1.0 0.0"/>
        </transform>
        <fov value="24"/>
        <speed value="100"/>
    </camera>

    <model name="Area">
        <vertex position="100.0 425.0 -273.0"/>
        <vertex position="-100.0 425.0 -273.0"/>
        <vertex position="-100.0 425.0 -223.0"/>
        <vertex position="100.0 425.0 -223.0"/>

        <index value="0"/>
        <index value="1"/>
        <index value="3"/>
        <index value="3"/>
        <index value="1"/>
        <index value="2"/>

        <material type="emission">
            <emission value="1.0 1.0 1.0"/>
            <emission_strength value="50.0"/>
        </material>
    </model>

    <model type="obj" name="Plane">
        <filename value="../../meshes/checker_plane.obj"/>
        <transform type="world">
            <scale value="100 100 100"/>
            <translation value="0.0 0.0 0.0"/>
            <rotation value="0.0 0.0 0.0"/>
        </transform>
        <material type="lambertian">
            <albedo value="1.0 1.0 1.0"/>
        </material>
    </model>

    <!-- <model type="obj" name="Sphere">
        <filename value="../../meshes/checker_sphere.obj"/>
        <transform type="world">
            <scale value="100 100 100"/>
            <translation value="0.0 0.0 0.0"/>
            <rotation value="0.0 0.0 0.0"/>
        </transform>
        <material type="checkerBump">
            <albedo value="1.0 1.0 1.0"/>
            <shade_smooth value="1"/>
        </material>
    </model> -->

    <model type="obj" name="Short Block">
        <filename value="../../meshes/oh_this_is_not_an_ordinary_cube.obj"/>
        <transform type="world">
            <scale value="80 80 80"/>
            <translation value="0 0 0"/>
            <rotation value="0 135 0"/>
        </transform>
        <material type="checkerBump">
            <albedo value="1 1 1"/>
            <inverse_normal value="1"/>
            <shade_smooth value="1"/>
        </material>
    </model>


</scene>